docs/docs_assets/images/logo.svg
formee/__init__.py
formee/__main__.py
formee/auth/check.py
formee/auth/hasher.py
formee/auth/login.py
formee/auth/register.py
formee/auth/user_jwt.py
formee/auth/validate.py
formee/auth/visitor_jwt.py
formee/auth/visitor_settings.py
formee/formTools/create.py
formee/formTools/deploy.py
formee/formTools/fill.py
formee/formTools/read.py
formee/formTools/responses.py
formee/formTools/validators.py
formee-0.1.6.dist-info/entry_points.txt
formee-0.1.6.dist-info/LICENSE
formee-0.1.6.dist-info/WHEEL
formee-0.1.6.dist-info/METADATA
formee-0.1.6.dist-info/RECORD
